LICENSE
MANIFEST.in
README.md
requirements.txt
setup.py
pick_up_tools/__init__.py
pick_up_tools.egg-info/PKG-INFO
pick_up_tools.egg-info/SOURCES.txt
pick_up_tools.egg-info/dependency_links.txt
pick_up_tools.egg-info/requires.txt
pick_up_tools.egg-info/top_level.txt
pick_up_tools/v0/__init__.py
pick_up_tools/v0/cv/__init__.py
pick_up_tools/v0/data/__init__.py
pick_up_tools/v0/data/wechat_message_bot.py
pick_up_tools/v0/data/table/__init__.py
pick_up_tools/v0/data/table/ali_odps.py
pick_up_tools/v0/data/table/ali_oss.py
pick_up_tools/v0/data/table/local_file.py
pick_up_tools/v0/nlp/__init__.py
pick_up_tools/v0/nlp/algorithm/__init__.py
pick_up_tools/v0/nlp/algorithm/keyword/__init__.py
pick_up_tools/v0/nlp/algorithm/keyword/tfidf.py
pick_up_tools/v0/nlp/algorithm/new_word_discovery/__init__.py
pick_up_tools/v0/nlp/algorithm/new_word_discovery/by_entropy/__init__.py
pick_up_tools/v0/nlp/algorithm/new_word_discovery/by_entropy/discovery_word.py
pick_up_tools/v0/nlp/algorithm/new_word_discovery/by_entropy/hyperparameters.py
pick_up_tools/v0/nlp/algorithm/new_word_discovery/by_entropy/modules.py
pick_up_tools/v0/nlp/algorithm/new_word_discovery/by_entropy/probability.py
pick_up_tools/v0/nlp/algorithm/new_word_discovery/by_entropy/requirements.txt
pick_up_tools/v0/nlp/algorithm/new_word_discovery/by_entropy/segment_entropy.py
pick_up_tools/v0/nlp/algorithm/new_word_discovery/by_entropy/tokenization.py
pick_up_tools/v0/nlp/algorithm/new_word_discovery/by_entropy/utils.py
pick_up_tools/v0/nlp/algorithm/new_word_discovery/by_entropy/data/hellonlp-words500.txt
pick_up_tools/v0/nlp/algorithm/new_word_discovery/by_entropy/data/smoothnlp-words500.txt
pick_up_tools/v0/nlp/algorithm/new_word_discovery/by_entropy/dict/vocabulary.txt
pick_up_tools/v0/nlp/algorithm/new_word_discovery/by_entropy/dict/vocabulary_word.txt
pick_up_tools/v0/nlp/algorithm/sentiment/__init__.py
pick_up_tools/v0/nlp/algorithm/sentiment/score.py
pick_up_tools/v0/nlp/algorithm/sentiment/by_bayes/__init__.py
pick_up_tools/v0/nlp/algorithm/sentiment/by_bayes/jiagunlp.py
pick_up_tools/v0/nlp/algorithm/sentiment/by_bayes/snow.py
pick_up_tools/v0/nlp/algorithm/sentiment/by_dict/__init__.py
