Metadata-Version: 2.1
Name: pick-up-tools
Version: 0.0.31
Summary: just for job
Home-page: https://gitee.com/mahaoyang/pick-up
Author: pick-up
Author-email: martinlord@foxmail.com
License: LICENSE.txt
Platform: UNKNOWN
Classifier: Development Status :: 3 - Alpha
Classifier: Operating System :: OS Independent
Classifier: Intended Audience :: Developers
Classifier: License :: OSI Approved :: Apache Software License
Classifier: Programming Language :: Python :: 3
Classifier: Programming Language :: Python :: 3 :: Only
Classifier: Topic :: Software Development :: Libraries
License-File: LICENSE
